gla/check_excel_id_integrity.py
gla/gla.py
gla/helper.py
gla/ref_map.py
pygla-0.0.2.dist-info/LICENSE
pygla-0.0.2.dist-info/METADATA
pygla-0.0.2.dist-info/WHEEL
pygla-0.0.2.dist-info/top_level.txt
pygla-0.0.2.dist-info/RECORD
