Metadata-Version: 2.1
Name: pygla
Version: 0.0.2
Summary: Automate group learning assessment
Author: rpb
Author-email: balandongiv@gmail.com
License-File: LICENSE
Requires-Dist: pandas
